odoo/addons/stock_depot/README.rst
odoo/addons/stock_depot/__init__.py
odoo/addons/stock_depot/__manifest__.py
odoo/addons/stock_depot/i18n/fr.po
odoo/addons/stock_depot/i18n/it.po
odoo/addons/stock_depot/i18n/stock_depot.pot
odoo/addons/stock_depot/models/__init__.py
odoo/addons/stock_depot/models/stock_depot.py
odoo/addons/stock_depot/readme/CONTRIBUTORS.md
odoo/addons/stock_depot/readme/DESCRIPTION.md
odoo/addons/stock_depot/security/ir.model.access.csv
odoo/addons/stock_depot/static/description/icon.png
odoo/addons/stock_depot/static/description/index.html
odoo/addons/stock_depot/views/stock_depot.xml
odoo_addon_stock_depot-18.0.1.0.0.2.dist-info/METADATA
odoo_addon_stock_depot-18.0.1.0.0.2.dist-info/WHEEL
odoo_addon_stock_depot-18.0.1.0.0.2.dist-info/top_level.txt
odoo_addon_stock_depot-18.0.1.0.0.2.dist-info/RECORD
